hwglance/__console__.py
hwglance/__init__.py
hwglance/__main__.py
hwglance-1.0.9.dist-info/LICENSE
hwglance-1.0.9.dist-info/METADATA
hwglance-1.0.9.dist-info/WHEEL
hwglance-1.0.9.dist-info/entry_points.txt
hwglance-1.0.9.dist-info/top_level.txt
hwglance-1.0.9.dist-info/RECORD
