Metadata-Version: 2.1
Name: hwglance
Version: 1.0.9
Summary: hwglance: Glance at your computer status
Home-page: https://github.com/NamasteJasutin/hwglance
Author: NamasteJasutin
Author-email: justin.duijn@outlook.com
License: MIT
Platform: UNKNOWN
Classifier: License :: OSI Approved :: MIT License
Classifier: Programming Language :: Python :: 3
Classifier: Programming Language :: Python :: 3.7
Classifier: Operating System :: OS Independent
